Metadata-Version: 2.1
Name: alexpubg
Version: 0.11
Summary: simple self checking
Author-email: alexchristophermcc@gmail.com
